pfweb/__init__.py
pfweb/app.py
pfweb/config.py
pfweb/constants.py
pfweb/static/css/bootstrap.min.css
pfweb/static/css/datatables.min.css
pfweb/static/css/jquery-ui.min.css
pfweb/static/css/main.css
pfweb/static/fonts/glyphicons-halflings-regular.eot
pfweb/static/fonts/glyphicons-halflings-regular.svg
pfweb/static/fonts/glyphicons-halflings-regular.ttf
pfweb/static/fonts/glyphicons-halflings-regular.woff
pfweb/static/fonts/glyphicons-halflings-regular.woff2
pfweb/static/js/bootstrap.min.js
pfweb/static/js/datatables.min.js
pfweb/static/js/jquery-3.1.1.min.js
pfweb/static/js/jquery-ui.min.js
pfweb/static/js/main.js
pfweb/templates/base.html
pfweb/templates/dash.html
pfweb/templates/edit.html
pfweb/templates/edit_rule.html
pfweb/templates/edit_table.html
pfweb/templates/error.html
pfweb/templates/login.html
pfweb/templates/pfinfo.html
pfweb/templates/rules.html
pfweb/templates/states.html
pfweb/templates/tables.html
pfweb-0.1.0.dev4.dist-info/DESCRIPTION.rst
pfweb-0.1.0.dev4.dist-info/METADATA
pfweb-0.1.0.dev4.dist-info/RECORD
pfweb-0.1.0.dev4.dist-info/WHEEL
pfweb-0.1.0.dev4.dist-info/metadata.json
pfweb-0.1.0.dev4.dist-info/top_level.txt
